{
  "a_comp_cor_00": {
    "CumulativeVarianceExplained": 0.0198167302,
    "Mask": "combined",
    "Method": "aCompCor",
    "Retained": true,
    "SingularValue": 65.8911785961,
    "VarianceExplained": 0.0198167302
  },
  "a_comp_cor_01": {
    "CumulativeVarianceExplained": 0.0377434005,
    "Mask": "combined",
    "Method": "aCompCor",
    "Retained": true,
    "SingularValue": 62.6702017943,
    "VarianceExplained": 0.0179266703
  },
  "a_comp_cor_02": {
    "CumulativeVarianceExplained": 0.0532281128,
    "Mask": "combined",
    "Method": "aCompCor",
    "Retained": true,
    "SingularValue": 58.24556309,
    "VarianceExplained": 0.0154847123
  },
  "a_comp_cor_03": {
    "CumulativeVarianceExplained": 0.0668890328,
    "Mask": "combined",
    "Method": "aCompCor",
    "Retained": true,
    "SingularValue": 54.7080522102,
    "VarianceExplained": 0.0136609201
  },
  "a_comp_cor_04": {
    "CumulativeVarianceExplained": 0.0775879062,
    "Mask": "combined",
    "Method": "aCompCor",
    "Retained": true,
    "SingularValue": 48.4150406483,
    "VarianceExplained": 0.0106988733
  },
  "a_comp_cor_05": {
    "CumulativeVarianceExplained": 0.0875683331,
    "Mask": "combined",
    "Method": "aCompCor",
    "Retained": true,
    "SingularValue": 46.7612203475,
    "VarianceExplained": 0.0099804269
  },
  "a_comp_cor_06": {
    "CumulativeVarianceExplained": 0.0971291366,
    "Mask": "combined",
    "Method": "aCompCor",
    "Retained": true,
    "SingularValue": 45.7676354289,
    "VarianceExplained": 0.0095608036
  },
  "a_comp_cor_07": {
    "CumulativeVarianceExplained": 0.1065592683,
    "Mask": "combined",
    "Method": "aCompCor",
    "Retained": true,
    "SingularValue": 45.4537957836,
    "VarianceExplained": 0.0094301317
  },
  "a_comp_cor_08": {
    "CumulativeVarianceExplained": 0.1158388161,
    "Mask": "combined",
    "Method": "aCompCor",
    "Retained": true,
    "SingularValue": 45.0894236363,
    "VarianceExplained": 0.0092795478
  },
  "a_comp_cor_09": {
    "CumulativeVarianceExplained": 0.1250172828,
    "Mask": "combined",
    "Method": "aCompCor",
    "Retained": true,
    "SingularValue": 44.8431742292,
    "VarianceExplained": 0.0091784667
  },
  "a_comp_cor_10": {
    "CumulativeVarianceExplained": 0.1340873821,
    "Mask": "combined",
    "Method": "aCompCor",
    "Retained": true,
    "SingularValue": 44.5776630571,
    "VarianceExplained": 0.0090700992
  },
  "a_comp_cor_11": {
    "CumulativeVarianceExplained": 0.1430506625,
    "Mask": "combined",
    "Method": "aCompCor",
    "Retained": true,
    "SingularValue": 44.314389485,
    "VarianceExplained": 0.0089632805
  },
  "a_comp_cor_12": {
    "CumulativeVarianceExplained": 0.1518604088,
    "Mask": "combined",
    "Method": "aCompCor",
    "Retained": true,
    "SingularValue": 43.9332142348,
    "VarianceExplained": 0.0088097463
  },
  "a_comp_cor_13": {
    "CumulativeVarianceExplained": 0.1605598234,
    "Mask": "combined",
    "Method": "aCompCor",
    "Retained": true,
    "SingularValue": 43.657241591,
    "VarianceExplained": 0.0086994146
  },
  "a_comp_cor_14": {
    "CumulativeVarianceExplained": 0.169215709,
    "Mask": "combined",
    "Method": "aCompCor",
    "Retained": true,
    "SingularValue": 43.547881375,
    "VarianceExplained": 0.0086558856
  },
  "a_comp_cor_15": {
    "CumulativeVarianceExplained": 0.1776895597,
    "Mask": "combined",
    "Method": "aCompCor",
    "Retained": true,
    "SingularValue": 43.087538207,
    "VarianceExplained": 0.0084738507
  },
  "a_comp_cor_16": {
    "CumulativeVarianceExplained": 0.1860694574,
    "Mask": "combined",
    "Method": "aCompCor",
    "Retained": true,
    "SingularValue": 42.8480080765,
    "VarianceExplained": 0.0083798977
  },
  "a_comp_cor_17": {
    "CumulativeVarianceExplained": 0.194410276,
    "Mask": "combined",
    "Method": "aCompCor",
    "Retained": true,
    "SingularValue": 42.7479817294,
    "VarianceExplained": 0.0083408186
  },
  "a_comp_cor_18": {
    "CumulativeVarianceExplained": 0.2026042089,
    "Mask": "combined",
    "Method": "aCompCor",
    "Retained": true,
    "SingularValue": 42.3699037594,
    "VarianceExplained": 0.0081939328
  },
  "a_comp_cor_19": {
    "CumulativeVarianceExplained": 0.2107328675,
    "Mask": "combined",
    "Method": "aCompCor",
    "Retained": true,
    "SingularValue": 42.2008036719,
    "VarianceExplained": 0.0081286587
  },
  "a_comp_cor_20": {
    "CumulativeVarianceExplained": 0.2187988534,
    "Mask": "combined",
    "Method": "aCompCor",
    "Retained": true,
    "SingularValue": 42.0378026098,
    "VarianceExplained": 0.0080659859
  },
  "a_comp_cor_21": {
    "CumulativeVarianceExplained": 0.2267800345,
    "Mask": "combined",
    "Method": "aCompCor",
    "Retained": true,
    "SingularValue": 41.8162285447,
    "VarianceExplained": 0.0079811811
  },
  "a_comp_cor_22": {
    "CumulativeVarianceExplained": 0.2346479423,
    "Mask": "combined",
    "Method": "aCompCor",
    "Retained": true,
    "SingularValue": 41.5184284849,
    "VarianceExplained": 0.0078679077
  },
  "a_comp_cor_23": {
    "CumulativeVarianceExplained": 0.242454373,
    "Mask": "combined",
    "Method": "aCompCor",
    "Retained": true,
    "SingularValue": 41.3559052732,
    "VarianceExplained": 0.0078064307
  },
  "a_comp_cor_24": {
    "CumulativeVarianceExplained": 0.2502172013,
    "Mask": "combined",
    "Method": "aCompCor",
    "Retained": true,
    "SingularValue": 41.2402481718,
    "VarianceExplained": 0.0077628284
  },
  "a_comp_cor_25": {
    "CumulativeVarianceExplained": 0.2579098281,
    "Mask": "combined",
    "Method": "aCompCor",
    "Retained": true,
    "SingularValue": 41.0533506926,
    "VarianceExplained": 0.0076926268
  },
  "a_comp_cor_26": {
    "CumulativeVarianceExplained": 0.2655597819,
    "Mask": "combined",
    "Method": "aCompCor",
    "Retained": true,
    "SingularValue": 40.9393253934,
    "VarianceExplained": 0.0076499537
  },
  "a_comp_cor_27": {
    "CumulativeVarianceExplained": 0.2731024958,
    "Mask": "combined",
    "Method": "aCompCor",
    "Retained": true,
    "SingularValue": 40.6513615293,
    "VarianceExplained": 0.0075427139
  },
  "a_comp_cor_28": {
    "CumulativeVarianceExplained": 0.280594006,
    "Mask": "combined",
    "Method": "aCompCor",
    "Retained": true,
    "SingularValue": 40.5131456173,
    "VarianceExplained": 0.0074915102
  },
  "a_comp_cor_29": {
    "CumulativeVarianceExplained": 0.2879934204,
    "Mask": "combined",
    "Method": "aCompCor",
    "Retained": true,
    "SingularValue": 40.2633544137,
    "VarianceExplained": 0.0073994144
  },
  "a_comp_cor_30": {
    "CumulativeVarianceExplained": 0.2953465445,
    "Mask": "combined",
    "Method": "aCompCor",
    "Retained": true,
    "SingularValue": 40.1372141116,
    "VarianceExplained": 0.0073531241
  },
  "a_comp_cor_31": {
    "CumulativeVarianceExplained": 0.3026171497,
    "Mask": "combined",
    "Method": "aCompCor",
    "Retained": true,
    "SingularValue": 39.9113629463,
    "VarianceExplained": 0.0072706052
  },
  "a_comp_cor_32": {
    "CumulativeVarianceExplained": 0.3098622703,
    "Mask": "combined",
    "Method": "aCompCor",
    "Retained": true,
    "SingularValue": 39.8413539527,
    "VarianceExplained": 0.0072451207
  },
  "a_comp_cor_33": {
    "CumulativeVarianceExplained": 0.3170612465,
    "Mask": "combined",
    "Method": "aCompCor",
    "Retained": true,
    "SingularValue": 39.714275481,
    "VarianceExplained": 0.0071989761
  },
  "a_comp_cor_34": {
    "CumulativeVarianceExplained": 0.3241466579,
    "Mask": "combined",
    "Method": "aCompCor",
    "Retained": true,
    "SingularValue": 39.3997816477,
    "VarianceExplained": 0.0070854114
  },
  "a_comp_cor_35": {
    "CumulativeVarianceExplained": 0.3311844282,
    "Mask": "combined",
    "Method": "aCompCor",
    "Retained": true,
    "SingularValue": 39.267099337,
    "VarianceExplained": 0.0070377703
  },
  "a_comp_cor_36": {
    "CumulativeVarianceExplained": 0.3381758669,
    "Mask": "combined",
    "Method": "aCompCor",
    "Retained": true,
    "SingularValue": 39.1376328776,
    "VarianceExplained": 0.0069914387
  },
  "a_comp_cor_37": {
    "CumulativeVarianceExplained": 0.3451488078,
    "Mask": "combined",
    "Method": "aCompCor",
    "Retained": true,
    "SingularValue": 39.0858236687,
    "VarianceExplained": 0.0069729409
  },
  "a_comp_cor_38": {
    "CumulativeVarianceExplained": 0.3520999845,
    "Mask": "combined",
    "Method": "aCompCor",
    "Retained": true,
    "SingularValue": 39.0247782808,
    "VarianceExplained": 0.0069511768
  },
  "a_comp_cor_39": {
    "CumulativeVarianceExplained": 0.3589970321,
    "Mask": "combined",
    "Method": "aCompCor",
    "Retained": true,
    "SingularValue": 38.8725372208,
    "VarianceExplained": 0.0068970476
  },
  "a_comp_cor_40": {
    "CumulativeVarianceExplained": 0.3658208262,
    "Mask": "combined",
    "Method": "aCompCor",
    "Retained": true,
    "SingularValue": 38.6655537148,
    "VarianceExplained": 0.0068237941
  },
  "a_comp_cor_41": {
    "CumulativeVarianceExplained": 0.3725881446,
    "Mask": "combined",
    "Method": "aCompCor",
    "Retained": true,
    "SingularValue": 38.5052177641,
    "VarianceExplained": 0.0067673184
  },
  "a_comp_cor_42": {
    "CumulativeVarianceExplained": 0.3793100818,
    "Mask": "combined",
    "Method": "aCompCor",
    "Retained": true,
    "SingularValue": 38.3758938085,
    "VarianceExplained": 0.0067219372
  },
  "a_comp_cor_43": {
    "CumulativeVarianceExplained": 0.3859614348,
    "Mask": "combined",
    "Method": "aCompCor",
    "Retained": true,
    "SingularValue": 38.1738776384,
    "VarianceExplained": 0.006651353
  },
  "a_comp_cor_44": {
    "CumulativeVarianceExplained": 0.3925759197,
    "Mask": "combined",
    "Method": "aCompCor",
    "Retained": true,
    "SingularValue": 38.0679326522,
    "VarianceExplained": 0.0066144849
  },
  "a_comp_cor_45": {
    "CumulativeVarianceExplained": 0.3991494492,
    "Mask": "combined",
    "Method": "aCompCor",
    "Retained": true,
    "SingularValue": 37.9498954014,
    "VarianceExplained": 0.0065735294
  },
  "a_comp_cor_46": {
    "CumulativeVarianceExplained": 0.4056727594,
    "Mask": "combined",
    "Method": "aCompCor",
    "Retained": true,
    "SingularValue": 37.8046564406,
    "VarianceExplained": 0.0065233103
  },
  "a_comp_cor_47": {
    "CumulativeVarianceExplained": 0.4120537214,
    "Mask": "combined",
    "Method": "aCompCor",
    "Retained": true,
    "SingularValue": 37.3899043815,
    "VarianceExplained": 0.0063809619
  },
  "a_comp_cor_48": {
    "CumulativeVarianceExplained": 0.418421803,
    "Mask": "combined",
    "Method": "aCompCor",
    "Retained": true,
    "SingularValue": 37.3521486643,
    "VarianceExplained": 0.0063680817
  },
  "a_comp_cor_49": {
    "CumulativeVarianceExplained": 0.4247743973,
    "Mask": "combined",
    "Method": "aCompCor",
    "Retained": true,
    "SingularValue": 37.3067000774,
    "VarianceExplained": 0.0063525942
  },
  "a_comp_cor_50": {
    "CumulativeVarianceExplained": 0.4310727458,
    "Mask": "combined",
    "Method": "aCompCor",
    "Retained": true,
    "SingularValue": 37.147075075,
    "VarianceExplained": 0.0062983486
  },
  "a_comp_cor_51": {
    "CumulativeVarianceExplained": 0.4373492394,
    "Mask": "combined",
    "Method": "aCompCor",
    "Retained": true,
    "SingularValue": 37.082569758,
    "VarianceExplained": 0.0062764936
  },
  "a_comp_cor_52": {
    "CumulativeVarianceExplained": 0.4435597098,
    "Mask": "combined",
    "Method": "aCompCor",
    "Retained": true,
    "SingularValue": 36.8870162071,
    "VarianceExplained": 0.0062104704
  },
  "a_comp_cor_53": {
    "CumulativeVarianceExplained": 0.4497236247,
    "Mask": "combined",
    "Method": "aCompCor",
    "Retained": true,
    "SingularValue": 36.7484979052,
    "VarianceExplained": 0.0061639148
  },
  "a_comp_cor_54": {
    "CumulativeVarianceExplained": 0.4558663484,
    "Mask": "combined",
    "Method": "aCompCor",
    "Retained": true,
    "SingularValue": 36.6852743592,
    "VarianceExplained": 0.0061427238
  },
  "a_comp_cor_55": {
    "CumulativeVarianceExplained": 0.4619154297,
    "Mask": "combined",
    "Method": "aCompCor",
    "Retained": true,
    "SingularValue": 36.4045769118,
    "VarianceExplained": 0.0060490813
  },
  "a_comp_cor_56": {
    "CumulativeVarianceExplained": 0.4679081827,
    "Mask": "combined",
    "Method": "aCompCor",
    "Retained": true,
    "SingularValue": 36.2346828647,
    "VarianceExplained": 0.0059927529
  },
  "a_comp_cor_57": {
    "CumulativeVarianceExplained": 0.4738857306,
    "Mask": "combined",
    "Method": "aCompCor",
    "Retained": true,
    "SingularValue": 36.1886856563,
    "VarianceExplained": 0.0059775479
  },
  "a_comp_cor_58": {
    "CumulativeVarianceExplained": 0.4797758393,
    "Mask": "combined",
    "Method": "aCompCor",
    "Retained": true,
    "SingularValue": 35.9230277102,
    "VarianceExplained": 0.0058901087
  },
  "a_comp_cor_59": {
    "CumulativeVarianceExplained": 0.4856161467,
    "Mask": "combined",
    "Method": "aCompCor",
    "Retained": true,
    "SingularValue": 35.7708392398,
    "VarianceExplained": 0.0058403074
  },
  "a_comp_cor_60": {
    "CumulativeVarianceExplained": 0.491430438,
    "Mask": "combined",
    "Method": "aCompCor",
    "Retained": true,
    "SingularValue": 35.691078638,
    "VarianceExplained": 0.0058142914
  },
  "a_comp_cor_61": {
    "CumulativeVarianceExplained": 0.4972222304,
    "Mask": "combined",
    "Method": "aCompCor",
    "Retained": true,
    "SingularValue": 35.621956619,
    "VarianceExplained": 0.0057917924
  },
  "a_comp_cor_62": {
    "CumulativeVarianceExplained": 0.5029366109,
    "Mask": "combined",
    "Method": "aCompCor",
    "Retained": true,
    "SingularValue": 35.3830979318,
    "VarianceExplained": 0.0057143805
  },
  "c_comp_cor_00": {
    "CumulativeVarianceExplained": 0.0905373608,
    "Mask": "CSF",
    "Method": "aCompCor",
    "Retained": true,
    "SingularValue": 139.7847388502,
    "VarianceExplained": 0.0905373608
  },
  "c_comp_cor_01": {
    "CumulativeVarianceExplained": 0.1729160266,
    "Mask": "CSF",
    "Method": "aCompCor",
    "Retained": true,
    "SingularValue": 133.3377802463,
    "VarianceExplained": 0.0823786657
  },
  "c_comp_cor_02": {
    "CumulativeVarianceExplained": 0.2465963234,
    "Mask": "CSF",
    "Method": "aCompCor",
    "Retained": true,
    "SingularValue": 126.1018701994,
    "VarianceExplained": 0.0736802969
  },
  "c_comp_cor_03": {
    "CumulativeVarianceExplained": 0.2949983331,
    "Mask": "CSF",
    "Method": "aCompCor",
    "Retained": true,
    "SingularValue": 102.2062704285,
    "VarianceExplained": 0.0484020096
  },
  "c_comp_cor_04": {
    "CumulativeVarianceExplained": 0.3366725218,
    "Mask": "CSF",
    "Method": "aCompCor",
    "Retained": true,
    "SingularValue": 94.8373523943,
    "VarianceExplained": 0.0416741887
  },
  "c_comp_cor_05": {
    "CumulativeVarianceExplained": 0.3660732033,
    "Mask": "CSF",
    "Method": "aCompCor",
    "Retained": true,
    "SingularValue": 79.6571094132,
    "VarianceExplained": 0.0294006815
  },
  "c_comp_cor_06": {
    "CumulativeVarianceExplained": 0.3904487377,
    "Mask": "CSF",
    "Method": "aCompCor",
    "Retained": true,
    "SingularValue": 72.5308750516,
    "VarianceExplained": 0.0243755344
  },
  "c_comp_cor_07": {
    "CumulativeVarianceExplained": 0.4084336157,
    "Mask": "CSF",
    "Method": "aCompCor",
    "Retained": true,
    "SingularValue": 62.3016563353,
    "VarianceExplained": 0.0179848781
  },
  "c_comp_cor_08": {
    "CumulativeVarianceExplained": 0.4230094607,
    "Mask": "CSF",
    "Method": "aCompCor",
    "Retained": true,
    "SingularValue": 56.0870649551,
    "VarianceExplained": 0.0145758449
  },
  "c_comp_cor_09": {
    "CumulativeVarianceExplained": 0.4373706908,
    "Mask": "CSF",
    "Method": "aCompCor",
    "Retained": true,
    "SingularValue": 55.672620652,
    "VarianceExplained": 0.0143612301
  },
  "c_comp_cor_10": {
    "CumulativeVarianceExplained": 0.4509885947,
    "Mask": "CSF",
    "Method": "aCompCor",
    "Retained": true,
    "SingularValue": 54.2126923639,
    "VarianceExplained": 0.0136179039
  },
  "c_comp_cor_11": {
    "CumulativeVarianceExplained": 0.4634083896,
    "Mask": "CSF",
    "Method": "aCompCor",
    "Retained": true,
    "SingularValue": 51.7729671815,
    "VarianceExplained": 0.0124197949
  },
  "c_comp_cor_12": {
    "CumulativeVarianceExplained": 0.47457322,
    "Mask": "CSF",
    "Method": "aCompCor",
    "Retained": true,
    "SingularValue": 49.0876124933,
    "VarianceExplained": 0.0111648304
  },
  "c_comp_cor_13": {
    "CumulativeVarianceExplained": 0.4852059301,
    "Mask": "CSF",
    "Method": "aCompCor",
    "Retained": true,
    "SingularValue": 47.9035645248,
    "VarianceExplained": 0.0106327101
  },
  "c_comp_cor_14": {
    "CumulativeVarianceExplained": 0.4955655425,
    "Mask": "CSF",
    "Method": "aCompCor",
    "Retained": true,
    "SingularValue": 47.2843690365,
    "VarianceExplained": 0.0103596124
  },
  "c_comp_cor_15": {
    "CumulativeVarianceExplained": 0.5042777101,
    "Mask": "CSF",
    "Method": "aCompCor",
    "Retained": true,
    "SingularValue": 43.361964944,
    "VarianceExplained": 0.0087121676
  },
  "dropped_0": {
    "CumulativeVarianceExplained": 0.2119004882,
    "Mask": "Edge",
    "Method": "EdgeRegressor",
    "Retained": false,
    "SingularValue": 123.7615377158,
    "VarianceExplained": 0.0053671295
  },
  "dropped_1": {
    "CumulativeVarianceExplained": 0.2172238909,
    "Mask": "Edge",
    "Method": "EdgeRegressor",
    "Retained": false,
    "SingularValue": 123.2563533736,
    "VarianceExplained": 0.0053234026
  },
  "dropped_10": {
    "CumulativeVarianceExplained": 0.2641991941,
    "Mask": "Edge",
    "Method": "EdgeRegressor",
    "Retained": false,
    "SingularValue": 120.9000824866,
    "VarianceExplained": 0.0051218149
  },
  "dropped_100": {
    "CumulativeVarianceExplained": 0.6753841751,
    "Mask": "Edge",
    "Method": "EdgeRegressor",
    "Retained": false,
    "SingularValue": 108.6044699033,
    "VarianceExplained": 0.0041330065
  },
  "dropped_101": {
    "CumulativeVarianceExplained": 0.6795067204,
    "Mask": "Edge",
    "Method": "EdgeRegressor",
    "Retained": false,
    "SingularValue": 108.4669375982,
    "VarianceExplained": 0.0041225453
  },
  "dropped_102": {
    "CumulativeVarianceExplained": 0.6836127004,
    "Mask": "Edge",
    "Method": "EdgeRegressor",
    "Retained": false,
    "SingularValue": 108.2487946502,
    "VarianceExplained": 0.0041059799
  },
  "dropped_103": {
    "CumulativeVarianceExplained": 0.6877100063,
    "Mask": "Edge",
    "Method": "EdgeRegressor",
    "Retained": false,
    "SingularValue": 108.1343946704,
    "VarianceExplained": 0.0040973059
  },
  "dropped_104": {
    "CumulativeVarianceExplained": 0.6917906007,
    "Mask": "Edge",
    "Method": "EdgeRegressor",
    "Retained": false,
    "SingularValue": 107.9136477406,
    "VarianceExplained": 0.0040805944
  },
  "dropped_105": {
    "CumulativeVarianceExplained": 0.6958654086,
    "Mask": "Edge",
    "Method": "EdgeRegressor",
    "Retained": false,
    "SingularValue": 107.8371074825,
    "VarianceExplained": 0.0040748079
  },
  "dropped_106": {
    "CumulativeVarianceExplained": 0.6999286592,
    "Mask": "Edge",
    "Method": "EdgeRegressor",
    "Retained": false,
    "SingularValue": 107.6840705337,
    "VarianceExplained": 0.0040632506
  },
  "dropped_107": {
    "CumulativeVarianceExplained": 0.7039902013,
    "Mask": "Edge",
    "Method": "EdgeRegressor",
    "Retained": false,
    "SingularValue": 107.6614272688,
    "VarianceExplained": 0.004061542
  },
  "dropped_108": {
    "CumulativeVarianceExplained": 0.7080419089,
    "Mask": "Edge",
    "Method": "EdgeRegressor",
    "Retained": false,
    "SingularValue": 107.5310055531,
    "VarianceExplained": 0.0040517076
  },
  "dropped_109": {
    "CumulativeVarianceExplained": 0.7120799839,
    "Mask": "Edge",
    "Method": "EdgeRegressor",
    "Retained": false,
    "SingularValue": 107.3499505673,
    "VarianceExplained": 0.004038075
  },
  "dropped_11": {
    "CumulativeVarianceExplained": 0.2692987773,
    "Mask": "Edge",
    "Method": "EdgeRegressor",
    "Retained": false,
    "SingularValue": 120.6374080215,
    "VarianceExplained": 0.0050995832
  },
  "dropped_110": {
    "CumulativeVarianceExplained": 0.7161075252,
    "Mask": "Edge",
    "Method": "EdgeRegressor",
    "Retained": false,
    "SingularValue": 107.2098438764,
    "VarianceExplained": 0.0040275414
  },
  "dropped_111": {
    "CumulativeVarianceExplained": 0.7201276142,
    "Mask": "Edge",
    "Method": "EdgeRegressor",
    "Retained": false,
    "SingularValue": 107.110609007,
    "VarianceExplained": 0.0040200889
  },
  "dropped_112": {
    "CumulativeVarianceExplained": 0.7241434239,
    "Mask": "Edge",
    "Method": "EdgeRegressor",
    "Retained": false,
    "SingularValue": 107.0535860094,
    "VarianceExplained": 0.0040158097
  },
  "dropped_113": {
    "CumulativeVarianceExplained": 0.7281540268,
    "Mask": "Edge",
    "Method": "EdgeRegressor",
    "Retained": false,
    "SingularValue": 106.9841625918,
    "VarianceExplained": 0.0040106029
  },
  "dropped_114": {
    "CumulativeVarianceExplained": 0.7321599301,
    "Mask": "Edge",
    "Method": "EdgeRegressor",
    "Retained": false,
    "SingularValue": 106.9214617235,
    "VarianceExplained": 0.0040059033
  },
  "dropped_115": {
    "CumulativeVarianceExplained": 0.7361568519,
    "Mask": "Edge",
    "Method": "EdgeRegressor",
    "Retained": false,
    "SingularValue": 106.8015333656,
    "VarianceExplained": 0.0039969219
  },
  "dropped_116": {
    "CumulativeVarianceExplained": 0.7401308362,
    "Mask": "Edge",
    "Method": "EdgeRegressor",
    "Retained": false,
    "SingularValue": 106.4946353212,
    "VarianceExplained": 0.0039739843
  },
  "dropped_117": {
    "CumulativeVarianceExplained": 0.7441032197,
    "Mask": "Edge",
    "Method": "EdgeRegressor",
    "Retained": false,
    "SingularValue": 106.4731839415,
    "VarianceExplained": 0.0039723835
  },
  "dropped_118": {
    "CumulativeVarianceExplained": 0.7480617201,
    "Mask": "Edge",
    "Method": "EdgeRegressor",
    "Retained": false,
    "SingularValue": 106.2869646513,
    "VarianceExplained": 0.0039585004
  },
  "dropped_119": {
    "CumulativeVarianceExplained": 0.7520116072,
    "Mask": "Edge",
    "Method": "EdgeRegressor",
    "Retained": false,
    "SingularValue": 106.171267319,
    "VarianceExplained": 0.0039498871
  },
  "dropped_12": {
    "CumulativeVarianceExplained": 0.2743838423,
    "Mask": "Edge",
    "Method": "EdgeRegressor",
    "Retained": false,
    "SingularValue": 120.4655625765,
    "VarianceExplained": 0.005085065
  },
  "dropped_120": {
    "CumulativeVarianceExplained": 0.755954213,
    "Mask": "Edge",
    "Method": "EdgeRegressor",
    "Retained": false,
    "SingularValue": 106.0733618554,
    "VarianceExplained": 0.0039426057
  },
  "dropped_121": {
    "CumulativeVarianceExplained": 0.7598821298,
    "Mask": "Edge",
    "Method": "EdgeRegressor",
    "Retained": false,
    "SingularValue": 105.8755799864,
    "VarianceExplained": 0.0039279169
  },
  "dropped_122": {
    "CumulativeVarianceExplained": 0.7638051516,
    "Mask": "Edge",
    "Method": "EdgeRegressor",
    "Retained": false,
    "SingularValue": 105.8095865848,
    "VarianceExplained": 0.0039230218
  },
  "dropped_123": {
    "CumulativeVarianceExplained": 0.7677118957,
    "Mask": "Edge",
    "Method": "EdgeRegressor",
    "Retained": false,
    "SingularValue": 105.589841812,
    "VarianceExplained": 0.0039067441
  },
  "dropped_124": {
    "CumulativeVarianceExplained": 0.7716139128,
    "Mask": "Edge",
    "Method": "EdgeRegressor",
    "Retained": false,
    "SingularValue": 105.5259438163,
    "VarianceExplained": 0.0039020171
  },
  "dropped_125": {
    "CumulativeVarianceExplained": 0.7755129131,
    "Mask": "Edge",
    "Method": "EdgeRegressor",
    "Retained": false,
    "SingularValue": 105.4851422124,
    "VarianceExplained": 0.0038990003
  },
  "dropped_126": {
    "CumulativeVarianceExplained": 0.7794053554,
    "Mask": "Edge",
    "Method": "EdgeRegressor",
    "Retained": false,
    "SingularValue": 105.396392412,
    "VarianceExplained": 0.0038924422
  },
  "dropped_127": {
    "CumulativeVarianceExplained": 0.7832820075,
    "Mask": "Edge",
    "Method": "EdgeRegressor",
    "Retained": false,
    "SingularValue": 105.1823993347,
    "VarianceExplained": 0.0038766521
  },
  "dropped_128": {
    "CumulativeVarianceExplained": 0.7871535042,
    "Mask": "Edge",
    "Method": "EdgeRegressor",
    "Retained": false,
    "SingularValue": 105.1124375246,
    "VarianceExplained": 0.0038714967
  },
  "dropped_129": {
    "CumulativeVarianceExplained": 0.7910180153,
    "Mask": "Edge",
    "Method": "EdgeRegressor",
    "Retained": false,
    "SingularValue": 105.0175632888,
    "VarianceExplained": 0.0038645111
  },
  "dropped_13": {
    "CumulativeVarianceExplained": 0.2794647923,
    "Mask": "Edge",
    "Method": "EdgeRegressor",
    "Retained": false,
    "SingularValue": 120.4168101102,
    "VarianceExplained": 0.00508095
  },
  "dropped_130": {
    "CumulativeVarianceExplained": 0.7948741438,
    "Mask": "Edge",
    "Method": "EdgeRegressor",
    "Retained": false,
    "SingularValue": 104.9036030779,
    "VarianceExplained": 0.0038561285
  },
  "dropped_131": {
    "CumulativeVarianceExplained": 0.7987193513,
    "Mask": "Edge",
    "Method": "EdgeRegressor",
    "Retained": false,
    "SingularValue": 104.7549492764,
    "VarianceExplained": 0.0038452075
  },
  "dropped_132": {
    "CumulativeVarianceExplained": 0.8025413081,
    "Mask": "Edge",
    "Method": "EdgeRegressor",
    "Retained": false,
    "SingularValue": 104.4377592947,
    "VarianceExplained": 0.0038219568
  },
  "dropped_133": {
    "CumulativeVarianceExplained": 0.8063593296,
    "Mask": "Edge",
    "Method": "EdgeRegressor",
    "Retained": false,
    "SingularValue": 104.3839779372,
    "VarianceExplained": 0.0038180215
  },
  "dropped_134": {
    "CumulativeVarianceExplained": 0.8101715777,
    "Mask": "Edge",
    "Method": "EdgeRegressor",
    "Retained": false,
    "SingularValue": 104.3050260054,
    "VarianceExplained": 0.0038122481
  },
  "dropped_135": {
    "CumulativeVarianceExplained": 0.8139815953,
    "Mask": "Edge",
    "Method": "EdgeRegressor",
    "Retained": false,
    "SingularValue": 104.2745077168,
    "VarianceExplained": 0.0038100176
  },
  "dropped_136": {
    "CumulativeVarianceExplained": 0.8177757504,
    "Mask": "Edge",
    "Method": "EdgeRegressor",
    "Retained": false,
    "SingularValue": 104.0572149816,
    "VarianceExplained": 0.0037941551
  },
  "dropped_137": {
    "CumulativeVarianceExplained": 0.8215668697,
    "Mask": "Edge",
    "Method": "EdgeRegressor",
    "Retained": false,
    "SingularValue": 104.015577462,
    "VarianceExplained": 0.0037911193
  },
  "dropped_138": {
    "CumulativeVarianceExplained": 0.82533798,
    "Mask": "Edge",
    "Method": "EdgeRegressor",
    "Retained": false,
    "SingularValue": 103.7407236292,
    "VarianceExplained": 0.0037711103
  },
  "dropped_139": {
    "CumulativeVarianceExplained": 0.8291074509,
    "Mask": "Edge",
    "Method": "EdgeRegressor",
    "Retained": false,
    "SingularValue": 103.7181736084,
    "VarianceExplained": 0.003769471
  },
  "dropped_14": {
    "CumulativeVarianceExplained": 0.2845170777,
    "Mask": "Edge",
    "Method": "EdgeRegressor",
    "Retained": false,
    "SingularValue": 120.076658803,
    "VarianceExplained": 0.0050522854
  },
  "dropped_140": {
    "CumulativeVarianceExplained": 0.8328657886,
    "Mask": "Edge",
    "Method": "EdgeRegressor",
    "Retained": false,
    "SingularValue": 103.5648922878,
    "VarianceExplained": 0.0037583377
  },
  "dropped_141": {
    "CumulativeVarianceExplained": 0.8366136,
    "Mask": "Edge",
    "Method": "EdgeRegressor",
    "Retained": false,
    "SingularValue": 103.4197590193,
    "VarianceExplained": 0.0037478114
  },
  "dropped_142": {
    "CumulativeVarianceExplained": 0.8403594052,
    "Mask": "Edge",
    "Method": "EdgeRegressor",
    "Retained": false,
    "SingularValue": 103.3920747344,
    "VarianceExplained": 0.0037458052
  },
  "dropped_143": {
    "CumulativeVarianceExplained": 0.8440899379,
    "Mask": "Edge",
    "Method": "EdgeRegressor",
    "Retained": false,
    "SingularValue": 103.18108311,
    "VarianceExplained": 0.0037305327
  },
  "dropped_144": {
    "CumulativeVarianceExplained": 0.8478152658,
    "Mask": "Edge",
    "Method": "EdgeRegressor",
    "Retained": false,
    "SingularValue": 103.109079655,
    "VarianceExplained": 0.0037253279
  },
  "dropped_145": {
    "CumulativeVarianceExplained": 0.851529767,
    "Mask": "Edge",
    "Method": "EdgeRegressor",
    "Retained": false,
    "SingularValue": 102.9591413509,
    "VarianceExplained": 0.0037145012
  },
  "dropped_146": {
    "CumulativeVarianceExplained": 0.8552267632,
    "Mask": "Edge",
    "Method": "EdgeRegressor",
    "Retained": false,
    "SingularValue": 102.7162507301,
    "VarianceExplained": 0.0036969962
  },
  "dropped_147": {
    "CumulativeVarianceExplained": 0.8589158851,
    "Mask": "Edge",
    "Method": "EdgeRegressor",
    "Retained": false,
    "SingularValue": 102.6068043474,
    "VarianceExplained": 0.0036891219
  },
  "dropped_148": {
    "CumulativeVarianceExplained": 0.8625897032,
    "Mask": "Edge",
    "Method": "EdgeRegressor",
    "Retained": false,
    "SingularValue": 102.393758086,
    "VarianceExplained": 0.0036738181
  },
  "dropped_149": {
    "CumulativeVarianceExplained": 0.866255797,
    "Mask": "Edge",
    "Method": "EdgeRegressor",
    "Retained": false,
    "SingularValue": 102.2860590913,
    "VarianceExplained": 0.0036660938
  },
  "dropped_15": {
    "CumulativeVarianceExplained": 0.2895668954,
    "Mask": "Edge",
    "Method": "EdgeRegressor",
    "Retained": false,
    "SingularValue": 120.0473308908,
    "VarianceExplained": 0.0050498177
  },
  "dropped_150": {
    "CumulativeVarianceExplained": 0.8699171381,
    "Mask": "Edge",
    "Method": "EdgeRegressor",
    "Retained": false,
    "SingularValue": 102.2197349783,
    "VarianceExplained": 0.003661341
  },
  "dropped_151": {
    "CumulativeVarianceExplained": 0.8735697869,
    "Mask": "Edge",
    "Method": "EdgeRegressor",
    "Retained": false,
    "SingularValue": 102.0983254343,
    "VarianceExplained": 0.0036526488
  },
  "dropped_152": {
    "CumulativeVarianceExplained": 0.8772142203,
    "Mask": "Edge",
    "Method": "EdgeRegressor",
    "Retained": false,
    "SingularValue": 101.9834430563,
    "VarianceExplained": 0.0036444334
  },
  "dropped_153": {
    "CumulativeVarianceExplained": 0.8808517762,
    "Mask": "Edge",
    "Method": "EdgeRegressor",
    "Retained": false,
    "SingularValue": 101.8871691283,
    "VarianceExplained": 0.0036375559
  },
  "dropped_154": {
    "CumulativeVarianceExplained": 0.8844774681,
    "Mask": "Edge",
    "Method": "EdgeRegressor",
    "Retained": false,
    "SingularValue": 101.720879615,
    "VarianceExplained": 0.0036256919
  },
  "dropped_155": {
    "CumulativeVarianceExplained": 0.8880945264,
    "Mask": "Edge",
    "Method": "EdgeRegressor",
    "Retained": false,
    "SingularValue": 101.5996963899,
    "VarianceExplained": 0.0036170583
  },
  "dropped_156": {
    "CumulativeVarianceExplained": 0.8916985203,
    "Mask": "Edge",
    "Method": "EdgeRegressor",
    "Retained": false,
    "SingularValue": 101.4160473221,
    "VarianceExplained": 0.0036039939
  },
  "dropped_157": {
    "CumulativeVarianceExplained": 0.8952908267,
    "Mask": "Edge",
    "Method": "EdgeRegressor",
    "Retained": false,
    "SingularValue": 101.2514722719,
    "VarianceExplained": 0.0035923064
  },
  "dropped_158": {
    "CumulativeVarianceExplained": 0.8988667458,
    "Mask": "Edge",
    "Method": "EdgeRegressor",
    "Retained": false,
    "SingularValue": 101.0202635138,
    "VarianceExplained": 0.003575919
  },
  "dropped_159": {
    "CumulativeVarianceExplained": 0.9024321603,
    "Mask": "Edge",
    "Method": "EdgeRegressor",
    "Retained": false,
    "SingularValue": 100.8717781834,
    "VarianceExplained": 0.0035654146
  },
  "dropped_16": {
    "CumulativeVarianceExplained": 0.2946103756,
    "Mask": "Edge",
    "Method": "EdgeRegressor",
    "Retained": false,
    "SingularValue": 119.9719785083,
    "VarianceExplained": 0.0050434803
  },
  "dropped_160": {
    "CumulativeVarianceExplained": 0.9059920617,
    "Mask": "Edge",
    "Method": "EdgeRegressor",
    "Retained": false,
    "SingularValue": 100.7937586401,
    "VarianceExplained": 0.0035599014
  },
  "dropped_161": {
    "CumulativeVarianceExplained": 0.9095383302,
    "Mask": "Edge",
    "Method": "EdgeRegressor",
    "Retained": false,
    "SingularValue": 100.6005759754,
    "VarianceExplained": 0.0035462685
  },
  "dropped_162": {
    "CumulativeVarianceExplained": 0.9130762527,
    "Mask": "Edge",
    "Method": "EdgeRegressor",
    "Retained": false,
    "SingularValue": 100.4821262747,
    "VarianceExplained": 0.0035379225
  },
  "dropped_163": {
    "CumulativeVarianceExplained": 0.9166006083,
    "Mask": "Edge",
    "Method": "EdgeRegressor",
    "Retained": false,
    "SingularValue": 100.2892807157,
    "VarianceExplained": 0.0035243556
  },
  "dropped_164": {
    "CumulativeVarianceExplained": 0.9201181816,
    "Mask": "Edge",
    "Method": "EdgeRegressor",
    "Retained": false,
    "SingularValue": 100.1927365651,
    "VarianceExplained": 0.0035175733
  },
  "dropped_165": {
    "CumulativeVarianceExplained": 0.9236312892,
    "Mask": "Edge",
    "Method": "EdgeRegressor",
    "Retained": false,
    "SingularValue": 100.129115999,
    "VarianceExplained": 0.0035131076
  },
  "dropped_166": {
    "CumulativeVarianceExplained": 0.9271259195,
    "Mask": "Edge",
    "Method": "EdgeRegressor",
    "Retained": false,
    "SingularValue": 99.8654535745,
    "VarianceExplained": 0.0034946303
  },
  "dropped_167": {
    "CumulativeVarianceExplained": 0.9306064737,
    "Mask": "Edge",
    "Method": "EdgeRegressor",
    "Retained": false,
    "SingularValue": 99.6641247062,
    "VarianceExplained": 0.0034805542
  },
  "dropped_168": {
    "CumulativeVarianceExplained": 0.9340827774,
    "Mask": "Edge",
    "Method": "EdgeRegressor",
    "Retained": false,
    "SingularValue": 99.6032508886,
    "VarianceExplained": 0.0034763037
  },
  "dropped_169": {
    "CumulativeVarianceExplained": 0.9375505897,
    "Mask": "Edge",
    "Method": "EdgeRegressor",
    "Retained": false,
    "SingularValue": 99.4815288154,
    "VarianceExplained": 0.0034678123
  },
  "dropped_17": {
    "CumulativeVarianceExplained": 0.2996331532,
    "Mask": "Edge",
    "Method": "EdgeRegressor",
    "Retained": false,
    "SingularValue": 119.7254916458,
    "VarianceExplained": 0.0050227775
  },
  "dropped_170": {
    "CumulativeVarianceExplained": 0.9410087176,
    "Mask": "Edge",
    "Method": "EdgeRegressor",
    "Retained": false,
    "SingularValue": 99.3425219731,
    "VarianceExplained": 0.0034581279
  },
  "dropped_171": {
    "CumulativeVarianceExplained": 0.9444535623,
    "Mask": "Edge",
    "Method": "EdgeRegressor",
    "Retained": false,
    "SingularValue": 99.1515440391,
    "VarianceExplained": 0.0034448447
  },
  "dropped_172": {
    "CumulativeVarianceExplained": 0.9478898657,
    "Mask": "Edge",
    "Method": "EdgeRegressor",
    "Retained": false,
    "SingularValue": 99.02854834,
    "VarianceExplained": 0.0034363035
  },
  "dropped_173": {
    "CumulativeVarianceExplained": 0.9513059138,
    "Mask": "Edge",
    "Method": "EdgeRegressor",
    "Retained": false,
    "SingularValue": 98.7362534893,
    "VarianceExplained": 0.0034160481
  },
  "dropped_174": {
    "CumulativeVarianceExplained": 0.9547128209,
    "Mask": "Edge",
    "Method": "EdgeRegressor",
    "Retained": false,
    "SingularValue": 98.6040610967,
    "VarianceExplained": 0.0034069071
  },
  "dropped_175": {
    "CumulativeVarianceExplained": 0.9581118018,
    "Mask": "Edge",
    "Method": "EdgeRegressor",
    "Retained": false,
    "SingularValue": 98.4892937044,
    "VarianceExplained": 0.0033989809
  },
  "dropped_176": {
    "CumulativeVarianceExplained": 0.9615066513,
    "Mask": "Edge",
    "Method": "EdgeRegressor",
    "Retained": false,
    "SingularValue": 98.4294191169,
    "VarianceExplained": 0.0033948495
  },
  "dropped_177": {
    "CumulativeVarianceExplained": 0.9648896913,
    "Mask": "Edge",
    "Method": "EdgeRegressor",
    "Retained": false,
    "SingularValue": 98.2580689814,
    "VarianceExplained": 0.00338304
  },
  "dropped_178": {
    "CumulativeVarianceExplained": 0.9682583005,
    "Mask": "Edge",
    "Method": "EdgeRegressor",
    "Retained": false,
    "SingularValue": 98.0482780043,
    "VarianceExplained": 0.0033686092
  },
  "dropped_179": {
    "CumulativeVarianceExplained": 0.9716095112,
    "Mask": "Edge",
    "Method": "EdgeRegressor",
    "Retained": false,
    "SingularValue": 97.7947468444,
    "VarianceExplained": 0.0033512107
  },
  "dropped_18": {
    "CumulativeVarianceExplained": 0.3046422299,
    "Mask": "Edge",
    "Method": "EdgeRegressor",
    "Retained": false,
    "SingularValue": 119.5620908206,
    "VarianceExplained": 0.0050090767
  },
  "dropped_180": {
    "CumulativeVarianceExplained": 0.9749520614,
    "Mask": "Edge",
    "Method": "EdgeRegressor",
    "Retained": false,
    "SingularValue": 97.6683005684,
    "VarianceExplained": 0.0033425503
  },
  "dropped_181": {
    "CumulativeVarianceExplained": 0.9782818911,
    "Mask": "Edge",
    "Method": "EdgeRegressor",
    "Retained": false,
    "SingularValue": 97.4822779209,
    "VarianceExplained": 0.0033298297
  },
  "dropped_182": {
    "CumulativeVarianceExplained": 0.9815956511,
    "Mask": "Edge",
    "Method": "EdgeRegressor",
    "Retained": false,
    "SingularValue": 97.2467697285,
    "VarianceExplained": 0.00331376
  },
  "dropped_183": {
    "CumulativeVarianceExplained": 0.9848927034,
    "Mask": "Edge",
    "Method": "EdgeRegressor",
    "Retained": false,
    "SingularValue": 97.0013037729,
    "VarianceExplained": 0.0032970522
  },
  "dropped_184": {
    "CumulativeVarianceExplained": 0.9881632147,
    "Mask": "Edge",
    "Method": "EdgeRegressor",
    "Retained": false,
    "SingularValue": 96.6100899793,
    "VarianceExplained": 0.0032705113
  },
  "dropped_185": {
    "CumulativeVarianceExplained": 0.9914163951,
    "Mask": "Edge",
    "Method": "EdgeRegressor",
    "Retained": false,
    "SingularValue": 96.353774715,
    "VarianceExplained": 0.0032531804
  },
  "dropped_186": {
    "CumulativeVarianceExplained": 0.9946534108,
    "Mask": "Edge",
    "Method": "EdgeRegressor",
    "Retained": false,
    "SingularValue": 96.1140898482,
    "VarianceExplained": 0.0032370156
  },
  "dropped_187": {
    "CumulativeVarianceExplained": 0.9976389394,
    "Mask": "Edge",
    "Method": "EdgeRegressor",
    "Retained": false,
    "SingularValue": 92.3050111244,
    "VarianceExplained": 0.0029855286
  },
  "dropped_188": {
    "CumulativeVarianceExplained": 1.0,
    "Mask": "Edge",
    "Method": "EdgeRegressor",
    "Retained": false,
    "SingularValue": 82.0858359539,
    "VarianceExplained": 0.0023610606
  },
  "dropped_189": {
    "CumulativeVarianceExplained": 1.0,
    "Mask": "Edge",
    "Method": "EdgeRegressor",
    "Retained": false,
    "SingularValue": 0.0,
    "VarianceExplained": 0.0
  },
  "dropped_19": {
    "CumulativeVarianceExplained": 0.3096178934,
    "Mask": "Edge",
    "Method": "EdgeRegressor",
    "Retained": false,
    "SingularValue": 119.1626518699,
    "VarianceExplained": 0.0049756635
  },
  "dropped_190": {
    "CumulativeVarianceExplained": 1.0,
    "Mask": "Edge",
    "Method": "EdgeRegressor",
    "Retained": false,
    "SingularValue": 0.0,
    "VarianceExplained": 0.0
  },
  "dropped_191": {
    "CumulativeVarianceExplained": 1.0,
    "Mask": "Edge",
    "Method": "EdgeRegressor",
    "Retained": false,
    "SingularValue": 0.0,
    "VarianceExplained": 0.0
  },
  "dropped_192": {
    "CumulativeVarianceExplained": 1.0,
    "Mask": "Edge",
    "Method": "EdgeRegressor",
    "Retained": false,
    "SingularValue": 0.0,
    "VarianceExplained": 0.0
  },
  "dropped_193": {
    "CumulativeVarianceExplained": 1.0,
    "Mask": "Edge",
    "Method": "EdgeRegressor",
    "Retained": false,
    "SingularValue": 0.0,
    "VarianceExplained": 0.0
  },
  "dropped_2": {
    "CumulativeVarianceExplained": 0.2225372814,
    "Mask": "Edge",
    "Method": "EdgeRegressor",
    "Retained": false,
    "SingularValue": 123.1403903681,
    "VarianceExplained": 0.0053133905
  },
  "dropped_20": {
    "CumulativeVarianceExplained": 0.314578297,
    "Mask": "Edge",
    "Method": "EdgeRegressor",
    "Retained": false,
    "SingularValue": 118.979780474,
    "VarianceExplained": 0.0049604036
  },
  "dropped_21": {
    "CumulativeVarianceExplained": 0.3195275697,
    "Mask": "Edge",
    "Method": "EdgeRegressor",
    "Retained": false,
    "SingularValue": 118.8462142727,
    "VarianceExplained": 0.0049492728
  },
  "dropped_22": {
    "CumulativeVarianceExplained": 0.3244658257,
    "Mask": "Edge",
    "Method": "EdgeRegressor",
    "Retained": false,
    "SingularValue": 118.7138688563,
    "VarianceExplained": 0.004938256
  },
  "dropped_23": {
    "CumulativeVarianceExplained": 0.3294014514,
    "Mask": "Edge",
    "Method": "EdgeRegressor",
    "Retained": false,
    "SingularValue": 118.6822484195,
    "VarianceExplained": 0.0049356257
  },
  "dropped_24": {
    "CumulativeVarianceExplained": 0.3343116334,
    "Mask": "Edge",
    "Method": "EdgeRegressor",
    "Retained": false,
    "SingularValue": 118.3759431574,
    "VarianceExplained": 0.004910182
  },
  "dropped_25": {
    "CumulativeVarianceExplained": 0.3392159551,
    "Mask": "Edge",
    "Method": "EdgeRegressor",
    "Retained": false,
    "SingularValue": 118.30528131,
    "VarianceExplained": 0.0049043217
  },
  "dropped_26": {
    "CumulativeVarianceExplained": 0.3441122141,
    "Mask": "Edge",
    "Method": "EdgeRegressor",
    "Retained": false,
    "SingularValue": 118.2079951965,
    "VarianceExplained": 0.004896259
  },
  "dropped_27": {
    "CumulativeVarianceExplained": 0.3489806641,
    "Mask": "Edge",
    "Method": "EdgeRegressor",
    "Retained": false,
    "SingularValue": 117.8718265811,
    "VarianceExplained": 0.00486845
  },
  "dropped_28": {
    "CumulativeVarianceExplained": 0.3538407595,
    "Mask": "Edge",
    "Method": "EdgeRegressor",
    "Retained": false,
    "SingularValue": 117.7706462499,
    "VarianceExplained": 0.0048600955
  },
  "dropped_29": {
    "CumulativeVarianceExplained": 0.3586849405,
    "Mask": "Edge",
    "Method": "EdgeRegressor",
    "Retained": false,
    "SingularValue": 117.5776670152,
    "VarianceExplained": 0.004844181
  },
  "dropped_3": {
    "CumulativeVarianceExplained": 0.2278182326,
    "Mask": "Edge",
    "Method": "EdgeRegressor",
    "Retained": false,
    "SingularValue": 122.7639165862,
    "VarianceExplained": 0.0052809512
  },
  "dropped_30": {
    "CumulativeVarianceExplained": 0.3635227756,
    "Mask": "Edge",
    "Method": "EdgeRegressor",
    "Retained": false,
    "SingularValue": 117.5006274628,
    "VarianceExplained": 0.004837835
  },
  "dropped_31": {
    "CumulativeVarianceExplained": 0.3683460338,
    "Mask": "Edge",
    "Method": "EdgeRegressor",
    "Retained": false,
    "SingularValue": 117.3234747126,
    "VarianceExplained": 0.0048232583
  },
  "dropped_32": {
    "CumulativeVarianceExplained": 0.3731542381,
    "Mask": "Edge",
    "Method": "EdgeRegressor",
    "Retained": false,
    "SingularValue": 117.1402404711,
    "VarianceExplained": 0.0048082042
  },
  "dropped_33": {
    "CumulativeVarianceExplained": 0.3779464833,
    "Mask": "Edge",
    "Method": "EdgeRegressor",
    "Retained": false,
    "SingularValue": 116.9456779744,
    "VarianceExplained": 0.0047922452
  },
  "dropped_34": {
    "CumulativeVarianceExplained": 0.3827283657,
    "Mask": "Edge",
    "Method": "EdgeRegressor",
    "Retained": false,
    "SingularValue": 116.8191669992,
    "VarianceExplained": 0.0047818824
  },
  "dropped_35": {
    "CumulativeVarianceExplained": 0.3874957703,
    "Mask": "Edge",
    "Method": "EdgeRegressor",
    "Retained": false,
    "SingularValue": 116.6421892007,
    "VarianceExplained": 0.0047674046
  },
  "dropped_36": {
    "CumulativeVarianceExplained": 0.3922492756,
    "Mask": "Edge",
    "Method": "EdgeRegressor",
    "Retained": false,
    "SingularValue": 116.4720316308,
    "VarianceExplained": 0.0047535053
  },
  "dropped_37": {
    "CumulativeVarianceExplained": 0.3970013902,
    "Mask": "Edge",
    "Method": "EdgeRegressor",
    "Retained": false,
    "SingularValue": 116.4549920517,
    "VarianceExplained": 0.0047521146
  },
  "dropped_38": {
    "CumulativeVarianceExplained": 0.4017313579,
    "Mask": "Edge",
    "Method": "EdgeRegressor",
    "Retained": false,
    "SingularValue": 116.1833097663,
    "VarianceExplained": 0.0047299677
  },
  "dropped_39": {
    "CumulativeVarianceExplained": 0.4064546715,
    "Mask": "Edge",
    "Method": "EdgeRegressor",
    "Retained": false,
    "SingularValue": 116.1015583406,
    "VarianceExplained": 0.0047233136
  },
  "dropped_4": {
    "CumulativeVarianceExplained": 0.2330835333,
    "Mask": "Edge",
    "Method": "EdgeRegressor",
    "Retained": false,
    "SingularValue": 122.5818721828,
    "VarianceExplained": 0.0052653008
  },
  "dropped_40": {
    "CumulativeVarianceExplained": 0.4111722453,
    "Mask": "Edge",
    "Method": "EdgeRegressor",
    "Retained": false,
    "SingularValue": 116.0309938581,
    "VarianceExplained": 0.0047175739
  },
  "dropped_41": {
    "CumulativeVarianceExplained": 0.415878235,
    "Mask": "Edge",
    "Method": "EdgeRegressor",
    "Retained": false,
    "SingularValue": 115.8884473562,
    "VarianceExplained": 0.0047059897
  },
  "dropped_42": {
    "CumulativeVarianceExplained": 0.4205685793,
    "Mask": "Edge",
    "Method": "EdgeRegressor",
    "Retained": false,
    "SingularValue": 115.6956470053,
    "VarianceExplained": 0.0046903443
  },
  "dropped_43": {
    "CumulativeVarianceExplained": 0.4252396206,
    "Mask": "Edge",
    "Method": "EdgeRegressor",
    "Retained": false,
    "SingularValue": 115.4573297206,
    "VarianceExplained": 0.0046710412
  },
  "dropped_44": {
    "CumulativeVarianceExplained": 0.4299022962,
    "Mask": "Edge",
    "Method": "EdgeRegressor",
    "Retained": false,
    "SingularValue": 115.353894593,
    "VarianceExplained": 0.0046626757
  },
  "dropped_45": {
    "CumulativeVarianceExplained": 0.4345570226,
    "Mask": "Edge",
    "Method": "EdgeRegressor",
    "Retained": false,
    "SingularValue": 115.2555201245,
    "VarianceExplained": 0.0046547263
  },
  "dropped_46": {
    "CumulativeVarianceExplained": 0.4392041394,
    "Mask": "Edge",
    "Method": "EdgeRegressor",
    "Retained": false,
    "SingularValue": 115.1612718479,
    "VarianceExplained": 0.0046471168
  },
  "dropped_47": {
    "CumulativeVarianceExplained": 0.4438359266,
    "Mask": "Edge",
    "Method": "EdgeRegressor",
    "Retained": false,
    "SingularValue": 114.971171432,
    "VarianceExplained": 0.0046317872
  },
  "dropped_48": {
    "CumulativeVarianceExplained": 0.4484579684,
    "Mask": "Edge",
    "Method": "EdgeRegressor",
    "Retained": false,
    "SingularValue": 114.850157438,
    "VarianceExplained": 0.0046220418
  },
  "dropped_49": {
    "CumulativeVarianceExplained": 0.4530743896,
    "Mask": "Edge",
    "Method": "EdgeRegressor",
    "Retained": false,
    "SingularValue": 114.7803041075,
    "VarianceExplained": 0.0046164212
  },
  "dropped_5": {
    "CumulativeVarianceExplained": 0.2383349823,
    "Mask": "Edge",
    "Method": "EdgeRegressor",
    "Retained": false,
    "SingularValue": 122.420523714,
    "VarianceExplained": 0.005251449
  },
  "dropped_50": {
    "CumulativeVarianceExplained": 0.4576887183,
    "Mask": "Edge",
    "Method": "EdgeRegressor",
    "Retained": false,
    "SingularValue": 114.7542875679,
    "VarianceExplained": 0.0046143287
  },
  "dropped_51": {
    "CumulativeVarianceExplained": 0.4622770199,
    "Mask": "Edge",
    "Method": "EdgeRegressor",
    "Retained": false,
    "SingularValue": 114.4301945881,
    "VarianceExplained": 0.0045883016
  },
  "dropped_52": {
    "CumulativeVarianceExplained": 0.466858995,
    "Mask": "Edge",
    "Method": "EdgeRegressor",
    "Retained": false,
    "SingularValue": 114.3512776445,
    "VarianceExplained": 0.0045819751
  },
  "dropped_53": {
    "CumulativeVarianceExplained": 0.4714348514,
    "Mask": "Edge",
    "Method": "EdgeRegressor",
    "Retained": false,
    "SingularValue": 114.2749006726,
    "VarianceExplained": 0.0045758564
  },
  "dropped_54": {
    "CumulativeVarianceExplained": 0.4760031482,
    "Mask": "Edge",
    "Method": "EdgeRegressor",
    "Retained": false,
    "SingularValue": 114.1804664556,
    "VarianceExplained": 0.0045682968
  },
  "dropped_55": {
    "CumulativeVarianceExplained": 0.4805645874,
    "Mask": "Edge",
    "Method": "EdgeRegressor",
    "Retained": false,
    "SingularValue": 114.0947348956,
    "VarianceExplained": 0.0045614392
  },
  "dropped_56": {
    "CumulativeVarianceExplained": 0.4851044525,
    "Mask": "Edge",
    "Method": "EdgeRegressor",
    "Retained": false,
    "SingularValue": 113.8246008819,
    "VarianceExplained": 0.0045398652
  },
  "dropped_57": {
    "CumulativeVarianceExplained": 0.4896368067,
    "Mask": "Edge",
    "Method": "EdgeRegressor",
    "Retained": false,
    "SingularValue": 113.7304026468,
    "VarianceExplained": 0.0045323541
  },
  "dropped_58": {
    "CumulativeVarianceExplained": 0.4941580699,
    "Mask": "Edge",
    "Method": "EdgeRegressor",
    "Retained": false,
    "SingularValue": 113.5911646698,
    "VarianceExplained": 0.0045212632
  },
  "dropped_59": {
    "CumulativeVarianceExplained": 0.4986738779,
    "Mask": "Edge",
    "Method": "EdgeRegressor",
    "Retained": false,
    "SingularValue": 113.5226167946,
    "VarianceExplained": 0.004515808
  },
  "dropped_6": {
    "CumulativeVarianceExplained": 0.2435542497,
    "Mask": "Edge",
    "Method": "EdgeRegressor",
    "Retained": false,
    "SingularValue": 122.0448422761,
    "VarianceExplained": 0.0052192674
  },
  "dropped_60": {
    "CumulativeVarianceExplained": 0.503180927,
    "Mask": "Edge",
    "Method": "EdgeRegressor",
    "Retained": false,
    "SingularValue": 113.412468769,
    "VarianceExplained": 0.0045070491
  },
  "dropped_61": {
    "CumulativeVarianceExplained": 0.5076740589,
    "Mask": "Edge",
    "Method": "EdgeRegressor",
    "Retained": false,
    "SingularValue": 113.2372305558,
    "VarianceExplained": 0.0044931318
  },
  "dropped_62": {
    "CumulativeVarianceExplained": 0.5121597641,
    "Mask": "Edge",
    "Method": "EdgeRegressor",
    "Retained": false,
    "SingularValue": 113.1436084434,
    "VarianceExplained": 0.0044857053
  },
  "dropped_63": {
    "CumulativeVarianceExplained": 0.5166294728,
    "Mask": "Edge",
    "Method": "EdgeRegressor",
    "Retained": false,
    "SingularValue": 112.9416861817,
    "VarianceExplained": 0.0044697087
  },
  "dropped_64": {
    "CumulativeVarianceExplained": 0.521082412,
    "Mask": "Edge",
    "Method": "EdgeRegressor",
    "Retained": false,
    "SingularValue": 112.7296200277,
    "VarianceExplained": 0.0044529392
  },
  "dropped_65": {
    "CumulativeVarianceExplained": 0.5255299387,
    "Mask": "Edge",
    "Method": "EdgeRegressor",
    "Retained": false,
    "SingularValue": 112.6610872894,
    "VarianceExplained": 0.0044475267
  },
  "dropped_66": {
    "CumulativeVarianceExplained": 0.5299677934,
    "Mask": "Edge",
    "Method": "EdgeRegressor",
    "Retained": false,
    "SingularValue": 112.5385194855,
    "VarianceExplained": 0.0044378547
  },
  "dropped_67": {
    "CumulativeVarianceExplained": 0.5344017349,
    "Mask": "Edge",
    "Method": "EdgeRegressor",
    "Retained": false,
    "SingularValue": 112.4888910455,
    "VarianceExplained": 0.0044339415
  },
  "dropped_68": {
    "CumulativeVarianceExplained": 0.5388204604,
    "Mask": "Edge",
    "Method": "EdgeRegressor",
    "Retained": false,
    "SingularValue": 112.2957112037,
    "VarianceExplained": 0.0044187255
  },
  "dropped_69": {
    "CumulativeVarianceExplained": 0.5432303271,
    "Mask": "Edge",
    "Method": "EdgeRegressor",
    "Retained": false,
    "SingularValue": 112.1830885654,
    "VarianceExplained": 0.0044098668
  },
  "dropped_7": {
    "CumulativeVarianceExplained": 0.2487481903,
    "Mask": "Edge",
    "Method": "EdgeRegressor",
    "Retained": false,
    "SingularValue": 121.7483677091,
    "VarianceExplained": 0.0051939406
  },
  "dropped_70": {
    "CumulativeVarianceExplained": 0.5476367656,
    "Mask": "Edge",
    "Method": "EdgeRegressor",
    "Retained": false,
    "SingularValue": 112.1394732653,
    "VarianceExplained": 0.0044064384
  },
  "dropped_71": {
    "CumulativeVarianceExplained": 0.5520315961,
    "Mask": "Edge",
    "Method": "EdgeRegressor",
    "Retained": false,
    "SingularValue": 111.9916713593,
    "VarianceExplained": 0.0043948306
  },
  "dropped_72": {
    "CumulativeVarianceExplained": 0.5564088638,
    "Mask": "Edge",
    "Method": "EdgeRegressor",
    "Retained": false,
    "SingularValue": 111.7676732479,
    "VarianceExplained": 0.0043772677
  },
  "dropped_73": {
    "CumulativeVarianceExplained": 0.5607822011,
    "Mask": "Edge",
    "Method": "EdgeRegressor",
    "Retained": false,
    "SingularValue": 111.7174839807,
    "VarianceExplained": 0.0043733373
  },
  "dropped_74": {
    "CumulativeVarianceExplained": 0.5651325425,
    "Mask": "Edge",
    "Method": "EdgeRegressor",
    "Retained": false,
    "SingularValue": 111.4233800337,
    "VarianceExplained": 0.0043503414
  },
  "dropped_75": {
    "CumulativeVarianceExplained": 0.5694764666,
    "Mask": "Edge",
    "Method": "EdgeRegressor",
    "Retained": false,
    "SingularValue": 111.3411672578,
    "VarianceExplained": 0.0043439241
  },
  "dropped_76": {
    "CumulativeVarianceExplained": 0.5738171043,
    "Mask": "Edge",
    "Method": "EdgeRegressor",
    "Retained": false,
    "SingularValue": 111.2990424375,
    "VarianceExplained": 0.0043406377
  },
  "dropped_77": {
    "CumulativeVarianceExplained": 0.5781494284,
    "Mask": "Edge",
    "Method": "EdgeRegressor",
    "Retained": false,
    "SingularValue": 111.1924059934,
    "VarianceExplained": 0.0043323241
  },
  "dropped_78": {
    "CumulativeVarianceExplained": 0.5824736817,
    "Mask": "Edge",
    "Method": "EdgeRegressor",
    "Retained": false,
    "SingularValue": 111.0887870467,
    "VarianceExplained": 0.0043242534
  },
  "dropped_79": {
    "CumulativeVarianceExplained": 0.5867890743,
    "Mask": "Edge",
    "Method": "EdgeRegressor",
    "Retained": false,
    "SingularValue": 110.9749121407,
    "VarianceExplained": 0.0043153925
  },
  "dropped_8": {
    "CumulativeVarianceExplained": 0.2539283195,
    "Mask": "Edge",
    "Method": "EdgeRegressor",
    "Retained": false,
    "SingularValue": 121.5863881744,
    "VarianceExplained": 0.0051801293
  },
  "dropped_80": {
    "CumulativeVarianceExplained": 0.591097403,
    "Mask": "Edge",
    "Method": "EdgeRegressor",
    "Retained": false,
    "SingularValue": 110.8840493942,
    "VarianceExplained": 0.0043083288
  },
  "dropped_81": {
    "CumulativeVarianceExplained": 0.5953961768,
    "Mask": "Edge",
    "Method": "EdgeRegressor",
    "Retained": false,
    "SingularValue": 110.7610209905,
    "VarianceExplained": 0.0042987737
  },
  "dropped_82": {
    "CumulativeVarianceExplained": 0.599687268,
    "Mask": "Edge",
    "Method": "EdgeRegressor",
    "Retained": false,
    "SingularValue": 110.6620040519,
    "VarianceExplained": 0.0042910912
  },
  "dropped_83": {
    "CumulativeVarianceExplained": 0.6039729767,
    "Mask": "Edge",
    "Method": "EdgeRegressor",
    "Retained": false,
    "SingularValue": 110.5925791335,
    "VarianceExplained": 0.0042857088
  },
  "dropped_84": {
    "CumulativeVarianceExplained": 0.6082487198,
    "Mask": "Edge",
    "Method": "EdgeRegressor",
    "Retained": false,
    "SingularValue": 110.4639224422,
    "VarianceExplained": 0.0042757431
  },
  "dropped_85": {
    "CumulativeVarianceExplained": 0.6125173477,
    "Mask": "Edge",
    "Method": "EdgeRegressor",
    "Retained": false,
    "SingularValue": 110.3719730021,
    "VarianceExplained": 0.0042686279
  },
  "dropped_86": {
    "CumulativeVarianceExplained": 0.6167713443,
    "Mask": "Edge",
    "Method": "EdgeRegressor",
    "Retained": false,
    "SingularValue": 110.1826535124,
    "VarianceExplained": 0.0042539966
  },
  "dropped_87": {
    "CumulativeVarianceExplained": 0.6210175329,
    "Mask": "Edge",
    "Method": "EdgeRegressor",
    "Retained": false,
    "SingularValue": 110.0814891575,
    "VarianceExplained": 0.0042461886
  },
  "dropped_88": {
    "CumulativeVarianceExplained": 0.6252502366,
    "Mask": "Edge",
    "Method": "EdgeRegressor",
    "Retained": false,
    "SingularValue": 109.9065541001,
    "VarianceExplained": 0.0042327037
  },
  "dropped_89": {
    "CumulativeVarianceExplained": 0.6294673601,
    "Mask": "Edge",
    "Method": "EdgeRegressor",
    "Retained": false,
    "SingularValue": 109.7040898955,
    "VarianceExplained": 0.0042171235
  },
  "dropped_9": {
    "CumulativeVarianceExplained": 0.2590773793,
    "Mask": "Edge",
    "Method": "EdgeRegressor",
    "Retained": false,
    "SingularValue": 121.22121231,
    "VarianceExplained": 0.0051490597
  },
  "dropped_90": {
    "CumulativeVarianceExplained": 0.6336816859,
    "Mask": "Edge",
    "Method": "EdgeRegressor",
    "Retained": false,
    "SingularValue": 109.6676942967,
    "VarianceExplained": 0.0042143258
  },
  "dropped_91": {
    "CumulativeVarianceExplained": 0.6378923985,
    "Mask": "Edge",
    "Method": "EdgeRegressor",
    "Retained": false,
    "SingularValue": 109.6206722695,
    "VarianceExplained": 0.0042107127
  },
  "dropped_92": {
    "CumulativeVarianceExplained": 0.6420841346,
    "Mask": "Edge",
    "Method": "EdgeRegressor",
    "Retained": false,
    "SingularValue": 109.3733775054,
    "VarianceExplained": 0.0041917361
  },
  "dropped_93": {
    "CumulativeVarianceExplained": 0.6462732862,
    "Mask": "Edge",
    "Method": "EdgeRegressor",
    "Retained": false,
    "SingularValue": 109.3396537574,
    "VarianceExplained": 0.0041891516
  },
  "dropped_94": {
    "CumulativeVarianceExplained": 0.6504528329,
    "Mask": "Edge",
    "Method": "EdgeRegressor",
    "Retained": false,
    "SingularValue": 109.2142349475,
    "VarianceExplained": 0.0041795467
  },
  "dropped_95": {
    "CumulativeVarianceExplained": 0.6546281862,
    "Mask": "Edge",
    "Method": "EdgeRegressor",
    "Retained": false,
    "SingularValue": 109.159433441,
    "VarianceExplained": 0.0041753533
  },
  "dropped_96": {
    "CumulativeVarianceExplained": 0.6587999923,
    "Mask": "Edge",
    "Method": "EdgeRegressor",
    "Retained": false,
    "SingularValue": 109.1130551526,
    "VarianceExplained": 0.0041718061
  },
  "dropped_97": {
    "CumulativeVarianceExplained": 0.6629577194,
    "Mask": "Edge",
    "Method": "EdgeRegressor",
    "Retained": false,
    "SingularValue": 108.9287827343,
    "VarianceExplained": 0.0041577271
  },
  "dropped_98": {
    "CumulativeVarianceExplained": 0.6671065528,
    "Mask": "Edge",
    "Method": "EdgeRegressor",
    "Retained": false,
    "SingularValue": 108.8122165993,
    "VarianceExplained": 0.0041488334
  },
  "dropped_99": {
    "CumulativeVarianceExplained": 0.6712511686,
    "Mask": "Edge",
    "Method": "EdgeRegressor",
    "Retained": false,
    "SingularValue": 108.7568944238,
    "VarianceExplained": 0.0041446158
  },
  "edge_comp_00": {
    "CumulativeVarianceExplained": 0.0190688917,
    "Mask": "Edge",
    "Method": "EdgeRegressor",
    "Retained": true,
    "SingularValue": 233.2799345565,
    "VarianceExplained": 0.0190688917
  },
  "edge_comp_01": {
    "CumulativeVarianceExplained": 0.0368865846,
    "Mask": "Edge",
    "Method": "EdgeRegressor",
    "Retained": true,
    "SingularValue": 225.4968045143,
    "VarianceExplained": 0.0178176928
  },
  "edge_comp_02": {
    "CumulativeVarianceExplained": 0.0541188349,
    "Mask": "Edge",
    "Method": "EdgeRegressor",
    "Retained": true,
    "SingularValue": 221.7612473966,
    "VarianceExplained": 0.0172322503
  },
  "edge_comp_03": {
    "CumulativeVarianceExplained": 0.0709911282,
    "Mask": "Edge",
    "Method": "EdgeRegressor",
    "Retained": true,
    "SingularValue": 219.4328864568,
    "VarianceExplained": 0.0168722933
  },
  "edge_comp_04": {
    "CumulativeVarianceExplained": 0.0826886835,
    "Mask": "Edge",
    "Method": "EdgeRegressor",
    "Retained": true,
    "SingularValue": 182.7099558002,
    "VarianceExplained": 0.0116975553
  },
  "edge_comp_05": {
    "CumulativeVarianceExplained": 0.0935539248,
    "Mask": "Edge",
    "Method": "EdgeRegressor",
    "Retained": true,
    "SingularValue": 176.0898591582,
    "VarianceExplained": 0.0108652413
  },
  "edge_comp_06": {
    "CumulativeVarianceExplained": 0.1024540909,
    "Mask": "Edge",
    "Method": "EdgeRegressor",
    "Retained": true,
    "SingularValue": 159.3726203888,
    "VarianceExplained": 0.0089001661
  },
  "edge_comp_07": {
    "CumulativeVarianceExplained": 0.1101015649,
    "Mask": "Edge",
    "Method": "EdgeRegressor",
    "Retained": true,
    "SingularValue": 147.7316893694,
    "VarianceExplained": 0.007647474
  },
  "edge_comp_08": {
    "CumulativeVarianceExplained": 0.1176020437,
    "Mask": "Edge",
    "Method": "EdgeRegressor",
    "Retained": true,
    "SingularValue": 146.3049944819,
    "VarianceExplained": 0.0075004788
  },
  "edge_comp_09": {
    "CumulativeVarianceExplained": 0.1247925588,
    "Mask": "Edge",
    "Method": "EdgeRegressor",
    "Retained": true,
    "SingularValue": 143.2500096722,
    "VarianceExplained": 0.0071905151
  },
  "edge_comp_10": {
    "CumulativeVarianceExplained": 0.1317675069,
    "Mask": "Edge",
    "Method": "EdgeRegressor",
    "Retained": true,
    "SingularValue": 141.0863986879,
    "VarianceExplained": 0.0069749481
  },
  "edge_comp_11": {
    "CumulativeVarianceExplained": 0.1383055338,
    "Mask": "Edge",
    "Method": "EdgeRegressor",
    "Retained": true,
    "SingularValue": 136.5960088051,
    "VarianceExplained": 0.0065380269
  },
  "edge_comp_12": {
    "CumulativeVarianceExplained": 0.1444958892,
    "Mask": "Edge",
    "Method": "EdgeRegressor",
    "Retained": true,
    "SingularValue": 132.9145268464,
    "VarianceExplained": 0.0061903554
  },
  "edge_comp_13": {
    "CumulativeVarianceExplained": 0.150540214,
    "Mask": "Edge",
    "Method": "EdgeRegressor",
    "Retained": true,
    "SingularValue": 131.3374422442,
    "VarianceExplained": 0.0060443248
  },
  "edge_comp_14": {
    "CumulativeVarianceExplained": 0.1563874136,
    "Mask": "Edge",
    "Method": "EdgeRegressor",
    "Retained": true,
    "SingularValue": 129.1780188387,
    "VarianceExplained": 0.0058471996
  },
  "edge_comp_15": {
    "CumulativeVarianceExplained": 0.1621960757,
    "Mask": "Edge",
    "Method": "EdgeRegressor",
    "Retained": true,
    "SingularValue": 128.7516228719,
    "VarianceExplained": 0.005808662
  },
  "edge_comp_16": {
    "CumulativeVarianceExplained": 0.1679599057,
    "Mask": "Edge",
    "Method": "EdgeRegressor",
    "Retained": true,
    "SingularValue": 128.2537997107,
    "VarianceExplained": 0.00576383
  },
  "edge_comp_17": {
    "CumulativeVarianceExplained": 0.1736325231,
    "Mask": "Edge",
    "Method": "EdgeRegressor",
    "Retained": true,
    "SingularValue": 127.2349448685,
    "VarianceExplained": 0.0056726174
  },
  "edge_comp_18": {
    "CumulativeVarianceExplained": 0.1792319666,
    "Mask": "Edge",
    "Method": "EdgeRegressor",
    "Retained": true,
    "SingularValue": 126.4116479218,
    "VarianceExplained": 0.0055994435
  },
  "edge_comp_19": {
    "CumulativeVarianceExplained": 0.1847989495,
    "Mask": "Edge",
    "Method": "EdgeRegressor",
    "Retained": true,
    "SingularValue": 126.044703071,
    "VarianceExplained": 0.0055669828
  },
  "edge_comp_20": {
    "CumulativeVarianceExplained": 0.1902788387,
    "Mask": "Edge",
    "Method": "EdgeRegressor",
    "Retained": true,
    "SingularValue": 125.0548520048,
    "VarianceExplained": 0.0054798892
  },
  "edge_comp_21": {
    "CumulativeVarianceExplained": 0.1957248284,
    "Mask": "Edge",
    "Method": "EdgeRegressor",
    "Retained": true,
    "SingularValue": 124.6674470213,
    "VarianceExplained": 0.0054459897
  },
  "edge_comp_22": {
    "CumulativeVarianceExplained": 0.2011316059,
    "Mask": "Edge",
    "Method": "EdgeRegressor",
    "Retained": true,
    "SingularValue": 124.2178209989,
    "VarianceExplained": 0.0054067775
  },
  "edge_comp_23": {
    "CumulativeVarianceExplained": 0.2065333587,
    "Mask": "Edge",
    "Method": "EdgeRegressor",
    "Retained": true,
    "SingularValue": 124.1600884158,
    "VarianceExplained": 0.0054017529
  },
  "framewise_displacement": {
    "Units": "mm"
  },
  "rot_x": {
    "Description": "Rotation about left-right axis. Also known as \"pitch\".",
    "Units": "rad"
  },
  "rot_y": {
    "Description": "Rotation about anterior-posterior axis. Also known as \"roll\".",
    "Units": "rad"
  },
  "rot_z": {
    "Description": "Rotation about superior-inferior axis. Also known as \"yaw\".",
    "Units": "rad"
  },
  "t_comp_cor_00": {
    "CumulativeVarianceExplained": 0.2731065228,
    "Method": "tCompCor",
    "Retained": true,
    "SingularValue": 299.5372990451,
    "VarianceExplained": 0.2731065228
  },
  "t_comp_cor_01": {
    "CumulativeVarianceExplained": 0.5128991364,
    "Method": "tCompCor",
    "Retained": true,
    "SingularValue": 280.6743810359,
    "VarianceExplained": 0.2397926136
  },
  "trans_x": {
    "Description": "Translation along left-right axis.",
    "Units": "mm"
  },
  "trans_y": {
    "Description": "Translation along anterior-posterior axis.",
    "Units": "mm"
  },
  "trans_z": {
    "Description": "Translation along superior-inferior axis.",
    "Units": "mm"
  },
  "w_comp_cor_00": {
    "CumulativeVarianceExplained": 0.0139798448,
    "Mask": "WM",
    "Method": "aCompCor",
    "Retained": true,
    "SingularValue": 53.1232840994,
    "VarianceExplained": 0.0139798448
  },
  "w_comp_cor_01": {
    "CumulativeVarianceExplained": 0.0270432259,
    "Mask": "WM",
    "Method": "aCompCor",
    "Retained": true,
    "SingularValue": 51.3524938293,
    "VarianceExplained": 0.0130633811
  },
  "w_comp_cor_02": {
    "CumulativeVarianceExplained": 0.0382070652,
    "Mask": "WM",
    "Method": "aCompCor",
    "Retained": true,
    "SingularValue": 47.4723278025,
    "VarianceExplained": 0.0111638393
  },
  "w_comp_cor_03": {
    "CumulativeVarianceExplained": 0.0487662591,
    "Mask": "WM",
    "Method": "aCompCor",
    "Retained": true,
    "SingularValue": 46.1688570211,
    "VarianceExplained": 0.0105591939
  },
  "w_comp_cor_04": {
    "CumulativeVarianceExplained": 0.0592156765,
    "Mask": "WM",
    "Method": "aCompCor",
    "Retained": true,
    "SingularValue": 45.9282373672,
    "VarianceExplained": 0.0104494174
  },
  "w_comp_cor_05": {
    "CumulativeVarianceExplained": 0.0694220676,
    "Mask": "WM",
    "Method": "aCompCor",
    "Retained": true,
    "SingularValue": 45.3910094948,
    "VarianceExplained": 0.010206391
  },
  "w_comp_cor_06": {
    "CumulativeVarianceExplained": 0.079276258,
    "Mask": "WM",
    "Method": "aCompCor",
    "Retained": true,
    "SingularValue": 44.6009609074,
    "VarianceExplained": 0.0098541904
  },
  "w_comp_cor_07": {
    "CumulativeVarianceExplained": 0.088933472,
    "Mask": "WM",
    "Method": "aCompCor",
    "Retained": true,
    "SingularValue": 44.1529442361,
    "VarianceExplained": 0.009657214
  },
  "w_comp_cor_08": {
    "CumulativeVarianceExplained": 0.0985129398,
    "Mask": "WM",
    "Method": "aCompCor",
    "Retained": true,
    "SingularValue": 43.9748564693,
    "VarianceExplained": 0.0095794678
  },
  "w_comp_cor_09": {
    "CumulativeVarianceExplained": 0.108014467,
    "Mask": "WM",
    "Method": "aCompCor",
    "Retained": true,
    "SingularValue": 43.7955966054,
    "VarianceExplained": 0.0095015271
  },
  "w_comp_cor_10": {
    "CumulativeVarianceExplained": 0.1173841468,
    "Mask": "WM",
    "Method": "aCompCor",
    "Retained": true,
    "SingularValue": 43.490671706,
    "VarianceExplained": 0.0093696798
  },
  "w_comp_cor_11": {
    "CumulativeVarianceExplained": 0.1266263786,
    "Mask": "WM",
    "Method": "aCompCor",
    "Retained": true,
    "SingularValue": 43.1938752332,
    "VarianceExplained": 0.0092422318
  },
  "w_comp_cor_12": {
    "CumulativeVarianceExplained": 0.1357325524,
    "Mask": "WM",
    "Method": "aCompCor",
    "Retained": true,
    "SingularValue": 42.8747604408,
    "VarianceExplained": 0.0091061738
  },
  "w_comp_cor_13": {
    "CumulativeVarianceExplained": 0.1447728946,
    "Mask": "WM",
    "Method": "aCompCor",
    "Retained": true,
    "SingularValue": 42.7195015501,
    "VarianceExplained": 0.0090403423
  },
  "w_comp_cor_14": {
    "CumulativeVarianceExplained": 0.1536976486,
    "Mask": "WM",
    "Method": "aCompCor",
    "Retained": true,
    "SingularValue": 42.4455206661,
    "VarianceExplained": 0.0089247539
  },
  "w_comp_cor_15": {
    "CumulativeVarianceExplained": 0.1624873745,
    "Mask": "WM",
    "Method": "aCompCor",
    "Retained": true,
    "SingularValue": 42.1232050609,
    "VarianceExplained": 0.008789726
  },
  "w_comp_cor_16": {
    "CumulativeVarianceExplained": 0.1711243729,
    "Mask": "WM",
    "Method": "aCompCor",
    "Retained": true,
    "SingularValue": 41.7556414556,
    "VarianceExplained": 0.0086369984
  },
  "w_comp_cor_17": {
    "CumulativeVarianceExplained": 0.1796310827,
    "Mask": "WM",
    "Method": "aCompCor",
    "Retained": true,
    "SingularValue": 41.4395038655,
    "VarianceExplained": 0.0085067097
  },
  "w_comp_cor_18": {
    "CumulativeVarianceExplained": 0.1881133746,
    "Mask": "WM",
    "Method": "aCompCor",
    "Retained": true,
    "SingularValue": 41.3799868898,
    "VarianceExplained": 0.008482292
  },
  "w_comp_cor_19": {
    "CumulativeVarianceExplained": 0.196510998,
    "Mask": "WM",
    "Method": "aCompCor",
    "Retained": true,
    "SingularValue": 41.1729453381,
    "VarianceExplained": 0.0083976233
  },
  "w_comp_cor_20": {
    "CumulativeVarianceExplained": 0.204835801,
    "Mask": "WM",
    "Method": "aCompCor",
    "Retained": true,
    "SingularValue": 40.9940403276,
    "VarianceExplained": 0.0083248031
  },
  "w_comp_cor_21": {
    "CumulativeVarianceExplained": 0.2130604601,
    "Mask": "WM",
    "Method": "aCompCor",
    "Retained": true,
    "SingularValue": 40.7467235729,
    "VarianceExplained": 0.0082246591
  },
  "w_comp_cor_22": {
    "CumulativeVarianceExplained": 0.2211807994,
    "Mask": "WM",
    "Method": "aCompCor",
    "Retained": true,
    "SingularValue": 40.4874876464,
    "VarianceExplained": 0.0081203393
  },
  "w_comp_cor_23": {
    "CumulativeVarianceExplained": 0.2292360313,
    "Mask": "WM",
    "Method": "aCompCor",
    "Retained": true,
    "SingularValue": 40.3248503262,
    "VarianceExplained": 0.0080552319
  },
  "w_comp_cor_24": {
    "CumulativeVarianceExplained": 0.2372491246,
    "Mask": "WM",
    "Method": "aCompCor",
    "Retained": true,
    "SingularValue": 40.2192380323,
    "VarianceExplained": 0.0080130932
  },
  "w_comp_cor_25": {
    "CumulativeVarianceExplained": 0.2451975032,
    "Mask": "WM",
    "Method": "aCompCor",
    "Retained": true,
    "SingularValue": 40.0565012481,
    "VarianceExplained": 0.0079483786
  },
  "w_comp_cor_26": {
    "CumulativeVarianceExplained": 0.2530834633,
    "Mask": "WM",
    "Method": "aCompCor",
    "Retained": true,
    "SingularValue": 39.8989097167,
    "VarianceExplained": 0.0078859601
  },
  "w_comp_cor_27": {
    "CumulativeVarianceExplained": 0.2609089887,
    "Mask": "WM",
    "Method": "aCompCor",
    "Retained": true,
    "SingularValue": 39.7457313074,
    "VarianceExplained": 0.0078255254
  },
  "w_comp_cor_28": {
    "CumulativeVarianceExplained": 0.2686451685,
    "Mask": "WM",
    "Method": "aCompCor",
    "Retained": true,
    "SingularValue": 39.5181874512,
    "VarianceExplained": 0.0077361798
  },
  "w_comp_cor_29": {
    "CumulativeVarianceExplained": 0.2762696645,
    "Mask": "WM",
    "Method": "aCompCor",
    "Retained": true,
    "SingularValue": 39.2318974434,
    "VarianceExplained": 0.0076244961
  },
  "w_comp_cor_30": {
    "CumulativeVarianceExplained": 0.2838404009,
    "Mask": "WM",
    "Method": "aCompCor",
    "Retained": true,
    "SingularValue": 39.0933421335,
    "VarianceExplained": 0.0075707363
  },
  "w_comp_cor_31": {
    "CumulativeVarianceExplained": 0.2913246049,
    "Mask": "WM",
    "Method": "aCompCor",
    "Retained": true,
    "SingularValue": 38.8692848106,
    "VarianceExplained": 0.007484204
  },
  "w_comp_cor_32": {
    "CumulativeVarianceExplained": 0.298789704,
    "Mask": "WM",
    "Method": "aCompCor",
    "Retained": true,
    "SingularValue": 38.8196422646,
    "VarianceExplained": 0.0074650991
  },
  "w_comp_cor_33": {
    "CumulativeVarianceExplained": 0.3061885664,
    "Mask": "WM",
    "Method": "aCompCor",
    "Retained": true,
    "SingularValue": 38.647038085,
    "VarianceExplained": 0.0073988624
  },
  "w_comp_cor_34": {
    "CumulativeVarianceExplained": 0.313548052,
    "Mask": "WM",
    "Method": "aCompCor",
    "Retained": true,
    "SingularValue": 38.5440609409,
    "VarianceExplained": 0.0073594856
  },
  "w_comp_cor_35": {
    "CumulativeVarianceExplained": 0.3208389734,
    "Mask": "WM",
    "Method": "aCompCor",
    "Retained": true,
    "SingularValue": 38.3640941067,
    "VarianceExplained": 0.0072909214
  },
  "w_comp_cor_36": {
    "CumulativeVarianceExplained": 0.3280913871,
    "Mask": "WM",
    "Method": "aCompCor",
    "Retained": true,
    "SingularValue": 38.2626482682,
    "VarianceExplained": 0.0072524137
  },
  "w_comp_cor_37": {
    "CumulativeVarianceExplained": 0.3352426377,
    "Mask": "WM",
    "Method": "aCompCor",
    "Retained": true,
    "SingularValue": 37.9948504229,
    "VarianceExplained": 0.0071512506
  },
  "w_comp_cor_38": {
    "CumulativeVarianceExplained": 0.3423694615,
    "Mask": "WM",
    "Method": "aCompCor",
    "Retained": true,
    "SingularValue": 37.9299047612,
    "VarianceExplained": 0.0071268238
  },
  "w_comp_cor_39": {
    "CumulativeVarianceExplained": 0.3494567988,
    "Mask": "WM",
    "Method": "aCompCor",
    "Retained": true,
    "SingularValue": 37.8246823145,
    "VarianceExplained": 0.0070873372
  },
  "w_comp_cor_40": {
    "CumulativeVarianceExplained": 0.3565223128,
    "Mask": "WM",
    "Method": "aCompCor",
    "Retained": true,
    "SingularValue": 37.766402815,
    "VarianceExplained": 0.007065514
  },
  "w_comp_cor_41": {
    "CumulativeVarianceExplained": 0.363478823,
    "Mask": "WM",
    "Method": "aCompCor",
    "Retained": true,
    "SingularValue": 37.4739483645,
    "VarianceExplained": 0.0069565102
  },
  "w_comp_cor_42": {
    "CumulativeVarianceExplained": 0.3703981576,
    "Mask": "WM",
    "Method": "aCompCor",
    "Retained": true,
    "SingularValue": 37.3736838758,
    "VarianceExplained": 0.0069193346
  },
  "w_comp_cor_43": {
    "CumulativeVarianceExplained": 0.3772377379,
    "Mask": "WM",
    "Method": "aCompCor",
    "Retained": true,
    "SingularValue": 37.1576692362,
    "VarianceExplained": 0.0068395802
  },
  "w_comp_cor_44": {
    "CumulativeVarianceExplained": 0.383965968,
    "Mask": "WM",
    "Method": "aCompCor",
    "Retained": true,
    "SingularValue": 36.853959978,
    "VarianceExplained": 0.0067282302
  },
  "w_comp_cor_45": {
    "CumulativeVarianceExplained": 0.3906635557,
    "Mask": "WM",
    "Method": "aCompCor",
    "Retained": true,
    "SingularValue": 36.7699419328,
    "VarianceExplained": 0.0066975877
  },
  "w_comp_cor_46": {
    "CumulativeVarianceExplained": 0.397336577,
    "Mask": "WM",
    "Method": "aCompCor",
    "Retained": true,
    "SingularValue": 36.7024447951,
    "VarianceExplained": 0.0066730213
  },
  "w_comp_cor_47": {
    "CumulativeVarianceExplained": 0.4039817731,
    "Mask": "WM",
    "Method": "aCompCor",
    "Retained": true,
    "SingularValue": 36.6258441156,
    "VarianceExplained": 0.0066451962
  },
  "w_comp_cor_48": {
    "CumulativeVarianceExplained": 0.4105913642,
    "Mask": "WM",
    "Method": "aCompCor",
    "Retained": true,
    "SingularValue": 36.5275914831,
    "VarianceExplained": 0.0066095911
  },
  "w_comp_cor_49": {
    "CumulativeVarianceExplained": 0.4171533691,
    "Mask": "WM",
    "Method": "aCompCor",
    "Retained": true,
    "SingularValue": 36.3958622851,
    "VarianceExplained": 0.0065620048
  },
  "w_comp_cor_50": {
    "CumulativeVarianceExplained": 0.4236287131,
    "Mask": "WM",
    "Method": "aCompCor",
    "Retained": true,
    "SingularValue": 36.1547335431,
    "VarianceExplained": 0.0064753441
  },
  "w_comp_cor_51": {
    "CumulativeVarianceExplained": 0.430069822,
    "Mask": "WM",
    "Method": "aCompCor",
    "Retained": true,
    "SingularValue": 36.0590316918,
    "VarianceExplained": 0.0064411089
  },
  "w_comp_cor_52": {
    "CumulativeVarianceExplained": 0.4364515721,
    "Mask": "WM",
    "Method": "aCompCor",
    "Retained": true,
    "SingularValue": 35.8924940331,
    "VarianceExplained": 0.0063817501
  },
  "w_comp_cor_53": {
    "CumulativeVarianceExplained": 0.4427946365,
    "Mask": "WM",
    "Method": "aCompCor",
    "Retained": true,
    "SingularValue": 35.7835399445,
    "VarianceExplained": 0.0063430644
  },
  "w_comp_cor_54": {
    "CumulativeVarianceExplained": 0.4491072892,
    "Mask": "WM",
    "Method": "aCompCor",
    "Retained": true,
    "SingularValue": 35.6976548662,
    "VarianceExplained": 0.0063126526
  },
  "w_comp_cor_55": {
    "CumulativeVarianceExplained": 0.4554082161,
    "Mask": "WM",
    "Method": "aCompCor",
    "Retained": true,
    "SingularValue": 35.6644854059,
    "VarianceExplained": 0.0063009269
  },
  "w_comp_cor_56": {
    "CumulativeVarianceExplained": 0.4615580151,
    "Mask": "WM",
    "Method": "aCompCor",
    "Retained": true,
    "SingularValue": 35.2341825475,
    "VarianceExplained": 0.006149799
  },
  "w_comp_cor_57": {
    "CumulativeVarianceExplained": 0.4676584524,
    "Mask": "WM",
    "Method": "aCompCor",
    "Retained": true,
    "SingularValue": 35.09249313,
    "VarianceExplained": 0.0061004373
  },
  "w_comp_cor_58": {
    "CumulativeVarianceExplained": 0.4737286661,
    "Mask": "WM",
    "Method": "aCompCor",
    "Retained": true,
    "SingularValue": 35.0054553041,
    "VarianceExplained": 0.0060702137
  },
  "w_comp_cor_59": {
    "CumulativeVarianceExplained": 0.4797569508,
    "Mask": "WM",
    "Method": "aCompCor",
    "Retained": true,
    "SingularValue": 34.8843487019,
    "VarianceExplained": 0.0060282847
  },
  "w_comp_cor_60": {
    "CumulativeVarianceExplained": 0.4857348192,
    "Mask": "WM",
    "Method": "aCompCor",
    "Retained": true,
    "SingularValue": 34.7381681168,
    "VarianceExplained": 0.0059778683
  },
  "w_comp_cor_61": {
    "CumulativeVarianceExplained": 0.4916901831,
    "Mask": "WM",
    "Method": "aCompCor",
    "Retained": true,
    "SingularValue": 34.6727183985,
    "VarianceExplained": 0.0059553639
  },
  "w_comp_cor_62": {
    "CumulativeVarianceExplained": 0.4975922501,
    "Mask": "WM",
    "Method": "aCompCor",
    "Retained": true,
    "SingularValue": 34.5172199252,
    "VarianceExplained": 0.0059020671
  },
  "w_comp_cor_63": {
    "CumulativeVarianceExplained": 0.5034313633,
    "Mask": "WM",
    "Method": "aCompCor",
    "Retained": true,
    "SingularValue": 34.3326388367,
    "VarianceExplained": 0.0058391131
  }
}